{
  "fonts": [
    {"id": "ARIAL", "file": "resources/fonts/ARIAL.ttf", "size": "16"}
  ],

  "images": [
    {"id": "Ship", "file":  "resources/images/fighter.png"},
    {"id": "Bullet", "file":  "resources/images/fire.png"},
    {"id": "Heart", "file":  "resources/images/heart.png"},
    {"id": "Asteroid", "file":  "resources/images/asteroid.png"},
    {"id": "AsteroidG", "file":  "resources/images/asteroid_gold.png"}

  ],

  "sounds": [
    {"id": "Thrust", "file": "resources/sounds/thrust.wav"},
    {"id": "Explosion", "file": "resources/sounds/explosion.wav"},
    {"id": "GunShot", "file": "resources/sounds/gunshot.wav"},
    {"id": "BangSmall", "file": "resources/sounds/bangSmall.wav"},
    {"id": "BackGroundMusic", "file": "resources/sounds/Navesitas.wav"}



  ]
}